vfq_operators/__init__.py
vfq_operators/hive_custom.py
vfq_operators/vfq_ozone_operator.py
vfq_cdp_operators-0.0.10.dist-info/METADATA
vfq_cdp_operators-0.0.10.dist-info/WHEEL
vfq_cdp_operators-0.0.10.dist-info/RECORD
