Metadata-Version: 2.4
Name: vfq_cdp_operators
Version: 0.0.10
Summary: Custom Hive Operator for CDE
Author-email: Data Team <admin@example.com>
Requires-Python: >=3.7
Requires-Dist: apache-airflow-providers-common-sql
Requires-Dist: apache-airflow>=2.0
